{
    "森": {
        "hanzi": "森",
        "pinyin": "sēn",
        "literal": "",
        "english": "forest / Mori (Japanese surname)",
        "char_matches": {
            "森": {
                "hsk4": [
                    "森林"
                ]
            }
        },
        "pinyin_tones": "sen1",
        "function": "noun",
        "hsk_level": -1
    },
    "林": {
        "hanzi": "林",
        "pinyin": "lín",
        "literal": "",
        "english": "woods / forest / circle(s) (i.e. specific group of people) / a collection (of similar things) / surname Lin / Japanese surname Hayashi",
        "char_matches": {
            "林": {
                "hsk4": [
                    "森林"
                ],
                "hsk6": [
                    "园林"
                ]
            }
        },
        "pinyin_tones": "lin2",
        "function": "gender noun",
        "hsk_level": -1
    },
    "森林": {
        "hanzi": "森林",
        "pinyin": "sēn lín",
        "literal": "",
        "english": "forest",
        "char_matches": {
            "森": {
                "unknown": [
                    "森"
                ]
            },
            "林": {
                "hsk6": [
                    "园林"
                ],
                "unknown": [
                    "林"
                ]
            }
        },
        "pinyin_tones": "sen1 lin2",
        "function": "noun",
        "hsk_level": 4
    },
    "冷": {
        "hanzi": "冷",
        "pinyin": "lěng",
        "literal": "",
        "english": "cold / surname Leng",
        "char_matches": {
            "冷": {
                "hsk4": [
                    "冷静"
                ],
                "hsk5": [
                    "冷淡"
                ],
                "hsk6": [
                    "冷酷",
                    "冷落",
                    "冷却"
                ]
            }
        },
        "pinyin_tones": "leng3",
        "function": "adjective",
        "hsk_level": 1
    },
    "热": {
        "hanzi": "热",
        "pinyin": "rè",
        "literal": "",
        "english": "to warm up / to heat up / hot (of weather) / heat / fervent",
        "char_matches": {
            "热": {
                "hsk3": [
                    "热情"
                ],
                "hsk4": [
                    "热闹"
                ],
                "hsk5": [
                    "热爱",
                    "热烈",
                    "热心"
                ],
                "hsk6": [
                    "亲热",
                    "热泪盈眶",
                    "热门",
                    "炎热"
                ]
            }
        },
        "pinyin_tones": "re4",
        "function": "noun",
        "hsk_level": 1
    },
    "冰": {
        "hanzi": "冰",
        "pinyin": "bīng",
        "literal": "",
        "english": "ice / to chill sth / (of an object or substance) to feel cold / (of a person) cold / unfriendly / (slang) methamphetamine / variant of 冰[bing1]",
        "char_matches": {
            "冰": {
                "hsk3": [
                    "冰箱"
                ],
                "hsk5": [
                    "冰激凌"
                ],
                "hsk6": [
                    "冰雹"
                ],
                "unknown": [
                    "冰淇淋"
                ]
            }
        },
        "pinyin_tones": "bing1",
        "function": "noun",
        "hsk_level": -1
    },
    "冰淇淋": {
        "hanzi": "冰淇淋",
        "pinyin": "bīng qí lín",
        "literal": "",
        "english": "ice cream",
        "char_matches": {
            "冰": {
                "hsk3": [
                    "冰箱"
                ],
                "hsk5": [
                    "冰激凌"
                ],
                "hsk6": [
                    "冰雹"
                ],
                "unknown": [
                    "冰"
                ]
            },
            "淋": {
                "hsk6": [
                    "淋"
                ]
            }
        },
        "pinyin_tones": "bing1 qi2 lin2",
        "function": "proper noun",
        "hsk_level": -1
    },
    "西": {
        "hanzi": "西",
        "pinyin": "xī",
        "literal": "",
        "english": "the West / abbr. for Spain 西班牙[Xi1 ban1 ya2] / Spanish / west",
        "char_matches": {
            "西": {
                "hsk1": [
                    "东西"
                ],
                "hsk2": [
                    "西瓜"
                ],
                "hsk4": [
                    "西红柿"
                ],
                "hsk6": [
                    "东张西望"
                ],
                "unknown": [
                    "东南西北"
                ]
            }
        },
        "pinyin_tones": "xi1",
        "function": "surname",
        "hsk_level": 3
    },
    "北": {
        "hanzi": "北",
        "pinyin": "běi",
        "literal": "",
        "english": "north / (classical) to be defeated",
        "char_matches": {
            "北": {
                "hsk1": [
                    "北京"
                ],
                "hsk3": [
                    "北方"
                ],
                "hsk6": [
                    "北极",
                    "南辕北辙"
                ],
                "unknown": [
                    "东南西北"
                ]
            }
        },
        "pinyin_tones": "bei3",
        "function": "place noun",
        "hsk_level": -1
    },
    "东": {
        "hanzi": "东",
        "pinyin": "dōng",
        "literal": "",
        "english": "east / host (i.e. sitting on east side of guest) / landlord / surname Dong",
        "char_matches": {
            "东": {
                "hsk1": [
                    "东西"
                ],
                "hsk4": [
                    "房东"
                ],
                "hsk6": [
                    "东道主",
                    "东张西望",
                    "股东"
                ],
                "unknown": [
                    "东南西北",
                    "广东",
                    "东方学院"
                ]
            }
        },
        "pinyin_tones": "dong1",
        "function": "place noun",
        "hsk_level": 3
    },
    "南": {
        "hanzi": "南",
        "pinyin": "nán",
        "literal": "",
        "english": "south / surname Nan",
        "char_matches": {
            "南": {
                "hsk6": [
                    "南辕北辙",
                    "指南针"
                ],
                "unknown": [
                    "东南西北"
                ]
            }
        },
        "pinyin_tones": "nan2",
        "function": "place noun",
        "hsk_level": 3
    },
    "东南西北": {
        "hanzi": "东南西北",
        "pinyin": "dōng nán xī běi",
        "literal": "",
        "english": "east, south, west and north / all directions",
        "char_matches": {
            "东": {
                "hsk1": [
                    "东西"
                ],
                "hsk3": [
                    "东"
                ],
                "hsk4": [
                    "房东"
                ],
                "hsk6": [
                    "东道主",
                    "东张西望",
                    "股东"
                ],
                "unknown": [
                    "广东",
                    "东方学院"
                ]
            },
            "南": {
                "hsk3": [
                    "南"
                ],
                "hsk6": [
                    "南辕北辙",
                    "指南针"
                ]
            },
            "西": {
                "hsk1": [
                    "东西"
                ],
                "hsk2": [
                    "西瓜"
                ],
                "hsk3": [
                    "西"
                ],
                "hsk4": [
                    "西红柿"
                ],
                "hsk6": [
                    "东张西望"
                ]
            },
            "北": {
                "hsk1": [
                    "北京"
                ],
                "unknown": [
                    "北"
                ],
                "hsk3": [
                    "北方"
                ],
                "hsk6": [
                    "北极",
                    "南辕北辙"
                ]
            }
        },
        "pinyin_tones": "dong1 nan2 xi1 bei3",
        "function": "place noun",
        "hsk_level": -1
    },
    "百": {
        "hanzi": "百",
        "pinyin": "bǎi",
        "literal": "",
        "english": "hundred / numerous / all kinds of / surname Bai",
        "char_matches": {
            "百": {
                "hsk4": [
                    "百分之"
                ],
                "hsk5": [
                    "老百姓"
                ],
                "hsk6": [
                    "千方百计"
                ],
                "unknown": [
                    "一百万"
                ]
            }
        },
        "pinyin_tones": "bai3",
        "function": "noun",
        "hsk_level": 2
    },
    "千": {
        "hanzi": "千",
        "pinyin": "qiān",
        "literal": "",
        "english": "thousand / see 鞦韆|秋千[qiu1 qian1]",
        "char_matches": {
            "千": {
                "hsk4": [
                    "千万"
                ],
                "hsk6": [
                    "千方百计"
                ],
                "unknown": [
                    "千米"
                ]
            }
        },
        "pinyin_tones": "qian1",
        "function": "number",
        "hsk_level": 2
    },
    "万": {
        "hanzi": "万",
        "pinyin": "wàn",
        "literal": "",
        "english": "see 万俟[Mo4 qi2] / ten thousand / a great number / surname Wan",
        "char_matches": {
            "万": {
                "hsk4": [
                    "千万"
                ],
                "hsk5": [
                    "万一"
                ],
                "hsk6": [
                    "万分"
                ],
                "unknown": [
                    "一百万"
                ]
            }
        },
        "pinyin_tones": "wan4",
        "function": "number",
        "hsk_level": 3
    },
    "真": {
        "hanzi": "真",
        "pinyin": "zhēn",
        "literal": "",
        "english": "really / truly / indeed / real / true / genuine",
        "char_matches": {
            "真": {
                "hsk3": [
                    "认真"
                ],
                "hsk4": [
                    "传真",
                    "真正"
                ],
                "hsk5": [
                    "天真",
                    "真实"
                ],
                "hsk6": [
                    "清真",
                    "真理",
                    "真相",
                    "真挚"
                ]
            }
        },
        "pinyin_tones": "zhen1",
        "function": "adverb",
        "hsk_level": 2
    },
    "来": {
        "hanzi": "来",
        "pinyin": "lái",
        "literal": "",
        "english": "to come / to arrive / to come round / ever since / next",
        "char_matches": {
            "来": {
                "hsk3": [
                    "后来",
                    "起来"
                ],
                "hsk4": [
                    "本来",
                    "从来",
                    "将来",
                    "来不及",
                    "来得及",
                    "来自",
                    "原来"
                ],
                "hsk5": [
                    "未来",
                    "以来"
                ],
                "hsk6": [
                    "近来",
                    "苦尽甘来",
                    "来历",
                    "来源",
                    "礼尚往来",
                    "历来",
                    "向来"
                ]
            }
        },
        "pinyin_tones": "lai2",
        "function": "verb",
        "hsk_level": 1
    },
    "欢迎": {
        "hanzi": "欢迎",
        "pinyin": "huān yíng",
        "literal": "",
        "english": "to welcome / welcome",
        "char_matches": {
            "欢": {
                "hsk1": [
                    "喜欢"
                ],
                "hsk6": [
                    "欢乐",
                    "联欢"
                ]
            },
            "迎": {
                "hsk5": [
                    "迎接"
                ],
                "hsk6": [
                    "迎面"
                ]
            }
        },
        "pinyin_tones": "huan1 ying2",
        "function": "verb",
        "hsk_level": 3
    },
    "为什么": {
        "hanzi": "为什么",
        "pinyin": "wèi shén me",
        "literal": "",
        "english": "why? / for what reason?",
        "char_matches": {
            "为": {
                "hsk2": [
                    "因为"
                ],
                "hsk3": [
                    "认为",
                    "为",
                    "为了"
                ],
                "hsk4": [
                    "成为",
                    "以为"
                ],
                "hsk5": [
                    "行为",
                    "作为"
                ],
                "hsk6": [
                    "见义勇为",
                    "迄今为止",
                    "人为",
                    "为难",
                    "为期",
                    "无能为力"
                ]
            },
            "什": {
                "unknown": [
                    "你姓什么"
                ],
                "hsk1": [
                    "什么"
                ]
            },
            "么": {
                "unknown": [
                    "么",
                    "你姓什么"
                ],
                "hsk1": [
                    "什么",
                    "怎么",
                    "怎么样"
                ],
                "hsk3": [
                    "多么"
                ]
            }
        },
        "pinyin_tones": "wei4 shen2 me",
        "function": "pronoun",
        "hsk_level": 2
    },
    "为": {
        "hanzi": "为",
        "pinyin": "wèi",
        "literal": "",
        "english": "as (in the capacity of) / to take sth as / to act as / to serve as / to behave as / to become / to be / to do / by (in the passive voice) / because of / for / to / variant of 為|为[wei2] / as (i.e. in the capacity of) / to take sth as / to act as / to serve as / to behave as / to become / to be / to do / variant of 為|为[wei4], because of / for / to",
        "char_matches": {
            "为": {
                "hsk2": [
                    "为什么",
                    "因为"
                ],
                "hsk3": [
                    "认为",
                    "为了"
                ],
                "hsk4": [
                    "成为",
                    "以为"
                ],
                "hsk5": [
                    "行为",
                    "作为"
                ],
                "hsk6": [
                    "见义勇为",
                    "迄今为止",
                    "人为",
                    "为难",
                    "为期",
                    "无能为力"
                ]
            }
        },
        "pinyin_tones": "wei4",
        "function": "preposition",
        "hsk_level": 3
    },
    "因为": {
        "hanzi": "因为",
        "pinyin": "yīn wèi",
        "literal": "",
        "english": "because / owing to / on account of",
        "char_matches": {
            "因": {
                "hsk4": [
                    "因此",
                    "原因"
                ],
                "hsk5": [
                    "因而",
                    "因素"
                ],
                "hsk6": [
                    "基因"
                ]
            },
            "为": {
                "hsk2": [
                    "为什么"
                ],
                "hsk3": [
                    "认为",
                    "为",
                    "为了"
                ],
                "hsk4": [
                    "成为",
                    "以为"
                ],
                "hsk5": [
                    "行为",
                    "作为"
                ],
                "hsk6": [
                    "见义勇为",
                    "迄今为止",
                    "人为",
                    "为难",
                    "为期",
                    "无能为力"
                ]
            }
        },
        "pinyin_tones": "yin1 wei4",
        "function": "complement",
        "hsk_level": 2
    },
    "分": {
        "hanzi": "分",
        "pinyin": "fēn",
        "literal": "",
        "english": "to divide / to separate / to distribute / to allocate / to distinguish (good and bad) / part or subdivision / fraction / one tenth (of certain units) / unit of length equivalent to 0.33 cm / minute (unit of time) / minute (angular measurement unit) / a point (in sports or games) / 0.01 yuan (unit of money) / part / share / ingredient / component",
        "char_matches": {
            "分": {
                "hsk1": [
                    "分钟"
                ],
                "hsk4": [
                    "百分之",
                    "部分",
                    "十分"
                ],
                "hsk5": [
                    "成分",
                    "充分",
                    "分别",
                    "分布",
                    "分配",
                    "分手",
                    "分析",
                    "过分"
                ],
                "hsk6": [
                    "处分",
                    "分辨",
                    "分寸",
                    "分红",
                    "分解",
                    "分裂",
                    "分泌",
                    "分明",
                    "分歧",
                    "分散",
                    "分量",
                    "划分",
                    "区分",
                    "万分"
                ],
                "unknown": [
                    "分公司"
                ]
            }
        },
        "pinyin_tones": "fen1",
        "function": "verb",
        "hsk_level": 3
    },
    "分公司": {
        "hanzi": "分公司",
        "pinyin": "fēn gōng sī",
        "literal": "",
        "english": "subsidiary company / branch office",
        "char_matches": {
            "分": {
                "hsk1": [
                    "分钟"
                ],
                "hsk3": [
                    "分"
                ],
                "hsk4": [
                    "百分之",
                    "部分",
                    "十分"
                ],
                "hsk5": [
                    "成分",
                    "充分",
                    "分别",
                    "分布",
                    "分配",
                    "分手",
                    "分析",
                    "过分"
                ],
                "hsk6": [
                    "处分",
                    "分辨",
                    "分寸",
                    "分红",
                    "分解",
                    "分裂",
                    "分泌",
                    "分明",
                    "分歧",
                    "分散",
                    "分量",
                    "划分",
                    "区分",
                    "万分"
                ]
            },
            "公": {
                "hsk2": [
                    "公共汽车",
                    "公司"
                ],
                "hsk3": [
                    "办公室",
                    "公斤",
                    "公园"
                ],
                "hsk4": [
                    "高速公路",
                    "公里"
                ],
                "hsk5": [
                    "公布",
                    "公开",
                    "公平",
                    "公寓",
                    "公元",
                    "公主",
                    "外公"
                ],
                "hsk6": [
                    "公安局",
                    "公道",
                    "公告",
                    "公关",
                    "公民",
                    "公然",
                    "公认",
                    "公式",
                    "公务",
                    "公正",
                    "公证"
                ]
            },
            "司": {
                "hsk2": [
                    "公司"
                ],
                "hsk3": [
                    "司机"
                ],
                "hsk6": [
                    "打官司",
                    "司法",
                    "司令"
                ]
            }
        },
        "pinyin_tones": "fen1 gong1 si1",
        "function": "noun",
        "hsk_level": -1
    },
    "老板": {
        "hanzi": "老板",
        "pinyin": "lǎo bǎn",
        "literal": "",
        "english": "variant of 老闆|老板[lao3 ban3] / Robam (brand) / boss / business proprietor",
        "char_matches": {
            "老": {
                "hsk1": [
                    "老师"
                ],
                "hsk4": [
                    "老虎"
                ],
                "hsk3": [
                    "老"
                ],
                "hsk5": [
                    "老百姓",
                    "老婆",
                    "老实",
                    "老鼠"
                ],
                "hsk6": [
                    "衰老"
                ],
                "unknown": [
                    "老朋友",
                    "老同学"
                ]
            },
            "板": {
                "hsk3": [
                    "黑板"
                ]
            }
        },
        "pinyin_tones": "lao3 ban3",
        "function": "noun",
        "hsk_level": 5
    },
    "让": {
        "hanzi": "让",
        "pinyin": "ràng",
        "literal": "",
        "english": "to yield / to permit / to let sb do sth / to have sb do sth / to make sb (feel sad etc) / by (indicates the agent in a passive clause, like 被[bei4])",
        "char_matches": {
            "让": {
                "hsk6": [
                    "让步",
                    "转让"
                ],
                "unknown": [
                    "请让一让"
                ]
            }
        },
        "pinyin_tones": "rang4",
        "function": "verb",
        "hsk_level": 2
    },
    "当然": {
        "hanzi": "当然",
        "pinyin": "dāng rán",
        "literal": "",
        "english": "only natural / as it should be / certainly / of course / without doubt",
        "char_matches": {
            "当": {
                "hsk4": [
                    "当",
                    "当时"
                ],
                "hsk5": [
                    "当地",
                    "当心",
                    "上当",
                    "相当"
                ],
                "hsk6": [
                    "不敢当",
                    "充当",
                    "当场",
                    "当初",
                    "当代",
                    "当面",
                    "当前",
                    "当事人",
                    "当务之急",
                    "当选",
                    "理所当然",
                    "恰当",
                    "妥当",
                    "正当"
                ]
            },
            "然": {
                "hsk2": [
                    "虽然"
                ],
                "hsk3": [
                    "然后",
                    "突然"
                ],
                "hsk4": [
                    "既然",
                    "竟然",
                    "然而",
                    "仍然",
                    "自然"
                ],
                "hsk5": [
                    "必然",
                    "不然",
                    "果然",
                    "忽然",
                    "居然",
                    "偶然",
                    "显然",
                    "依然"
                ],
                "hsk6": [
                    "公然",
                    "固然",
                    "恍然大悟",
                    "理所当然",
                    "茫然",
                    "天然气",
                    "一目了然",
                    "毅然"
                ]
            }
        },
        "pinyin_tones": "dang1 ran2",
        "function": "adverb",
        "hsk_level": 3
    },
    "想": {
        "hanzi": "想",
        "pinyin": "xiǎng",
        "literal": "",
        "english": "to think / to believe / to suppose / to wish / to want / to miss (feel wistful about the absence of sb or sth)",
        "char_matches": {
            "想": {
                "hsk4": [
                    "理想"
                ],
                "hsk5": [
                    "感想",
                    "幻想",
                    "梦想",
                    "思想",
                    "想念",
                    "想象"
                ],
                "hsk6": [
                    "空想",
                    "联想",
                    "设想",
                    "妄想",
                    "想方设法",
                    "着想"
                ],
                "unknown": [
                    "想一想"
                ]
            }
        },
        "pinyin_tones": "xiang3",
        "function": "verb",
        "hsk_level": 1
    },
    "能": {
        "hanzi": "能",
        "pinyin": "néng",
        "literal": "",
        "english": "can / to be able to / might possibly / ability / (physics) energy / surname Neng",
        "char_matches": {
            "能": {
                "hsk2": [
                    "可能"
                ],
                "hsk4": [
                    "能力"
                ],
                "hsk5": [
                    "功能",
                    "能干",
                    "能源"
                ],
                "hsk6": [
                    "本能",
                    "力所能及",
                    "难能可贵",
                    "能量",
                    "无能为力",
                    "性能",
                    "职能",
                    "智能"
                ]
            }
        },
        "pinyin_tones": "neng2",
        "function": "verb",
        "hsk_level": 1
    },
    "想一想": {
        "hanzi": "想一想",
        "pinyin": "xiǎng yī xiǎng",
        "literal": "",
        "english": "to think about",
        "char_matches": {
            "想": {
                "hsk4": [
                    "理想",
                    "理想"
                ],
                "hsk1": [
                    "想",
                    "想"
                ],
                "hsk5": [
                    "感想",
                    "幻想",
                    "梦想",
                    "思想",
                    "想念",
                    "想象",
                    "感想",
                    "幻想",
                    "梦想",
                    "思想",
                    "想念",
                    "想象"
                ],
                "hsk6": [
                    "空想",
                    "联想",
                    "设想",
                    "妄想",
                    "想方设法",
                    "着想",
                    "空想",
                    "联想",
                    "设想",
                    "妄想",
                    "想方设法",
                    "着想"
                ]
            },
            "一": {
                "hsk1": [
                    "一",
                    "一点儿"
                ],
                "hsk2": [
                    "第一",
                    "一起",
                    "一下"
                ],
                "hsk3": [
                    "一般",
                    "一边",
                    "一定",
                    "一共",
                    "一会儿",
                    "一样",
                    "一直"
                ],
                "hsk4": [
                    "一切"
                ],
                "hsk5": [
                    "统一",
                    "万一",
                    "唯一",
                    "一辈子",
                    "一旦",
                    "一律",
                    "一再",
                    "一致"
                ],
                "hsk6": [
                    "不屑一顾",
                    "一度",
                    "一帆风顺",
                    "一贯",
                    "一举两得",
                    "一流",
                    "一目了然",
                    "一如既往",
                    "一丝不苟",
                    "一向"
                ],
                "unknown": [
                    "请让一让",
                    "一百万"
                ]
            }
        },
        "pinyin_tones": "xiang3 yi1 xiang3",
        "function": "idiom",
        "hsk_level": -1
    },
    "可爱": {
        "hanzi": "可爱",
        "pinyin": "kě ài",
        "literal": "",
        "english": "adorable / cute / lovely",
        "char_matches": {
            "可": {
                "unknown": [
                    "可乐",
                    "我可以给你打电话"
                ],
                "hsk2": [
                    "可能",
                    "可以"
                ],
                "hsk4": [
                    "可怜",
                    "可是",
                    "可惜"
                ],
                "hsk5": [
                    "可见",
                    "可靠",
                    "可怕",
                    "宁可"
                ],
                "hsk6": [
                    "不可思议",
                    "可观",
                    "可口",
                    "可恶",
                    "可行",
                    "难能可贵",
                    "认可",
                    "许可"
                ]
            },
            "爱": {
                "hsk1": [
                    "爱"
                ],
                "hsk3": [
                    "爱好"
                ],
                "hsk4": [
                    "爱情"
                ],
                "hsk5": [
                    "爱护",
                    "爱惜",
                    "爱心",
                    "恋爱",
                    "亲爱",
                    "热爱",
                    "疼爱"
                ],
                "hsk6": [
                    "爱不释手",
                    "爱戴"
                ]
            }
        },
        "pinyin_tones": "ke3 ai4",
        "function": "verb",
        "hsk_level": 3
    },
    "家": {
        "hanzi": "家",
        "pinyin": "jiā",
        "literal": "",
        "english": "see 傢伙|家伙[jia1 huo5] / home / family / (polite) my (sister, uncle etc) / classifier for families or businesses / refers to the philosophical schools of pre-Han China / noun suffix for a specialist in some activity, such as a musician or revolutionary, corresponding to English -ist, -er, -ary or -ian",
        "char_matches": {
            "家": {
                "hsk3": [
                    "国家"
                ],
                "hsk2": [
                    "大家"
                ],
                "hsk4": [
                    "家具",
                    "作家"
                ],
                "hsk5": [
                    "家庭",
                    "家务",
                    "家乡",
                    "专家"
                ],
                "hsk6": [
                    "家常",
                    "家伙",
                    "家属",
                    "家喻户晓",
                    "人家",
                    "儒家"
                ],
                "unknown": [
                    "家人"
                ]
            }
        },
        "pinyin_tones": "jia1",
        "function": "classifier",
        "hsk_level": 1
    },
    "家人": {
        "hanzi": "家人",
        "pinyin": "jiā rén",
        "literal": "",
        "english": "household / (one's) family",
        "char_matches": {
            "家": {
                "hsk1": [
                    "家"
                ],
                "hsk3": [
                    "国家"
                ],
                "hsk2": [
                    "大家"
                ],
                "hsk4": [
                    "家具",
                    "作家"
                ],
                "hsk5": [
                    "家庭",
                    "家务",
                    "家乡",
                    "专家"
                ],
                "hsk6": [
                    "家常",
                    "家伙",
                    "家属",
                    "家喻户晓",
                    "人家",
                    "儒家"
                ]
            },
            "人": {
                "hsk1": [
                    "人"
                ],
                "hsk3": [
                    "别人",
                    "客人"
                ],
                "hsk5": [
                    "成人",
                    "敌人",
                    "个人",
                    "工人",
                    "人才",
                    "人口",
                    "人类",
                    "人民币",
                    "人生",
                    "人事",
                    "人物",
                    "人员",
                    "私人",
                    "行人",
                    "主人"
                ],
                "hsk6": [
                    "本人",
                    "当事人",
                    "丢人",
                    "法人",
                    "风土人情",
                    "夫人",
                    "迷人",
                    "人道",
                    "人格",
                    "人工",
                    "人家",
                    "人间",
                    "人士",
                    "人为",
                    "人性",
                    "人质"
                ],
                "unknown": [
                    "不是中国人"
                ]
            }
        },
        "pinyin_tones": "jia1 ren2",
        "function": "noun",
        "hsk_level": -1
    },
    "有": {
        "hanzi": "有",
        "pinyin": "yǒu",
        "literal": "",
        "english": "to have / there is / there are / to exist / to be",
        "char_matches": {
            "有": {
                "hsk1": [
                    "没有"
                ],
                "hsk3": [
                    "有名",
                    "只有"
                ],
                "hsk4": [
                    "所有",
                    "有趣"
                ],
                "hsk5": [
                    "有利"
                ],
                "hsk6": [
                    "固有",
                    "津津有味",
                    "岂有此理",
                    "拥有",
                    "有条不紊"
                ],
                "unknown": [
                    "有意思",
                    "有兴趣"
                ]
            }
        },
        "pinyin_tones": "you3",
        "function": "verb",
        "hsk_level": 1
    },
    "钱": {
        "hanzi": "钱",
        "pinyin": "qián",
        "literal": "",
        "english": "coin / money / unit of weight, one tenth of a tael 兩|两[liang3] / surname Qian",
        "char_matches": {
            "钱": {
                "hsk4": [
                    "零钱"
                ],
                "hsk6": [
                    "本钱",
                    "压岁钱"
                ]
            }
        },
        "pinyin_tones": "qian2",
        "function": "noun",
        "hsk_level": 1
    },
    "多少": {
        "hanzi": "多少",
        "pinyin": "duō shǎo",
        "literal": "",
        "english": "number / amount / somewhat / how much? / how many? / (phone number, student ID etc) what number?",
        "char_matches": {
            "多": {
                "hsk1": [
                    "多"
                ],
                "hsk3": [
                    "多么"
                ],
                "hsk4": [
                    "差不多",
                    "许多"
                ],
                "hsk5": [
                    "多亏",
                    "多余"
                ],
                "hsk6": [
                    "多元化",
                    "见多识广"
                ],
                "unknown": [
                    "多大"
                ]
            },
            "少": {
                "hsk1": [
                    "少"
                ],
                "hsk4": [
                    "减少",
                    "缺少",
                    "至少"
                ],
                "hsk5": [
                    "青少年"
                ]
            }
        },
        "pinyin_tones": "duo1 shao3",
        "function": "number",
        "hsk_level": 1
    },
    "几岁": {
        "hanzi": "几岁",
        "pinyin": "jǐ suì",
        "literal": "",
        "english": "how old are you? (familiar, or to a child)",
        "char_matches": {
            "几": {
                "hsk1": [
                    "几"
                ],
                "hsk3": [
                    "几乎"
                ]
            },
            "岁": {
                "hsk1": [
                    "岁"
                ],
                "hsk6": [
                    "岁月",
                    "压岁钱"
                ]
            }
        },
        "pinyin_tones": "ji3 sui4",
        "function": "number",
        "hsk_level": -1
    },
    "几": {
        "hanzi": "几",
        "pinyin": "jǐ",
        "literal": "",
        "english": "small table / almost / how much / how many / several / a few",
        "char_matches": {
            "几": {
                "hsk3": [
                    "几乎"
                ],
                "unknown": [
                    "几岁"
                ]
            }
        },
        "pinyin_tones": "ji3",
        "function": "number",
        "hsk_level": 1
    },
    "多大": {
        "hanzi": "多大",
        "pinyin": "duō dà",
        "literal": "",
        "english": "how old? / how big? / how much? / so big / that much",
        "char_matches": {
            "多": {
                "hsk1": [
                    "多",
                    "多少"
                ],
                "hsk3": [
                    "多么"
                ],
                "hsk4": [
                    "差不多",
                    "许多"
                ],
                "hsk5": [
                    "多亏",
                    "多余"
                ],
                "hsk6": [
                    "多元化",
                    "见多识广"
                ]
            },
            "大": {
                "hsk1": [
                    "大"
                ],
                "unknown": [
                    "大洋洲",
                    "加拿大",
                    "大学",
                    "澳大利亚"
                ],
                "hsk2": [
                    "大家"
                ],
                "hsk4": [
                    "大概",
                    "大使馆",
                    "大约",
                    "大夫"
                ],
                "hsk5": [
                    "大方",
                    "大厦",
                    "大象",
                    "大型",
                    "广大",
                    "巨大",
                    "扩大",
                    "伟大",
                    "重大"
                ],
                "hsk6": [
                    "博大精深",
                    "大不了",
                    "大臣",
                    "大伙儿",
                    "大肆",
                    "大体",
                    "大意",
                    "大致",
                    "放大",
                    "恍然大悟",
                    "庞大"
                ]
            }
        },
        "pinyin_tones": "duo1 da4",
        "function": [
            "number",
            "adjective"
        ],
        "hsk_level": [
            1,
            1
        ]
    },
    "大概": {
        "hanzi": "大概",
        "pinyin": "dà gài",
        "literal": "",
        "english": "roughly / probably / rough / approximate / about / general idea",
        "char_matches": {
            "大": {
                "hsk1": [
                    "大"
                ],
                "unknown": [
                    "大洋洲",
                    "加拿大",
                    "多大",
                    "大学",
                    "澳大利亚"
                ],
                "hsk2": [
                    "大家"
                ],
                "hsk4": [
                    "大使馆",
                    "大约",
                    "大夫"
                ],
                "hsk5": [
                    "大方",
                    "大厦",
                    "大象",
                    "大型",
                    "广大",
                    "巨大",
                    "扩大",
                    "伟大",
                    "重大"
                ],
                "hsk6": [
                    "博大精深",
                    "大不了",
                    "大臣",
                    "大伙儿",
                    "大肆",
                    "大体",
                    "大意",
                    "大致",
                    "放大",
                    "恍然大悟",
                    "庞大"
                ]
            },
            "概": {
                "hsk5": [
                    "概括",
                    "概念"
                ],
                "hsk6": [
                    "气概"
                ]
            }
        },
        "pinyin_tones": "da4 gai4",
        "function": "adverb",
        "hsk_level": 4
    },
    "地方": {
        "hanzi": "地方",
        "pinyin": "dì fāng",
        "literal": "",
        "english": "region / regional (away from the central administration) / local / area / place / space / room / territory",
        "char_matches": {
            "地": {
                "hsk3": [
                    "地",
                    "地铁",
                    "地图"
                ],
                "hsk4": [
                    "地点",
                    "地球",
                    "地址"
                ],
                "hsk5": [
                    "当地",
                    "地道",
                    "地理",
                    "地区",
                    "地毯",
                    "地位",
                    "地震",
                    "陆地",
                    "土地"
                ],
                "hsk6": [
                    "地步",
                    "地势",
                    "地质",
                    "耕地",
                    "基地",
                    "盆地",
                    "阵地",
                    "殖民地"
                ]
            },
            "方": {
                "hsk3": [
                    "北方",
                    "方便"
                ],
                "hsk4": [
                    "方法",
                    "方面",
                    "方向"
                ],
                "hsk5": [
                    "大方",
                    "对方",
                    "方",
                    "方案",
                    "方式",
                    "平方",
                    "双方"
                ],
                "hsk6": [
                    "比方",
                    "方位",
                    "方言",
                    "方圆",
                    "方针",
                    "官方",
                    "立方",
                    "千方百计",
                    "想方设法"
                ],
                "unknown": [
                    "东方学院"
                ]
            }
        },
        "pinyin_tones": "di4 fang1",
        "function": "noun",
        "hsk_level": 3
    },
    "请让一让": {
        "hanzi": "请让一让",
        "pinyin": "qǐng ràng yī ràng",
        "literal": "",
        "english": "please make way",
        "char_matches": {
            "请": {
                "hsk1": [
                    "请"
                ],
                "hsk3": [
                    "请假"
                ],
                "hsk4": [
                    "申请",
                    "邀请"
                ],
                "hsk5": [
                    "请求"
                ],
                "hsk6": [
                    "请柬",
                    "请教",
                    "请示",
                    "请帖"
                ],
                "unknown": [
                    "请坐",
                    "请进"
                ]
            },
            "让": {
                "hsk2": [
                    "让",
                    "让"
                ],
                "hsk6": [
                    "让步",
                    "转让",
                    "让步",
                    "转让"
                ]
            },
            "一": {
                "hsk1": [
                    "一",
                    "一点儿"
                ],
                "hsk2": [
                    "第一",
                    "一起",
                    "一下"
                ],
                "hsk3": [
                    "一般",
                    "一边",
                    "一定",
                    "一共",
                    "一会儿",
                    "一样",
                    "一直"
                ],
                "hsk4": [
                    "一切"
                ],
                "hsk5": [
                    "统一",
                    "万一",
                    "唯一",
                    "一辈子",
                    "一旦",
                    "一律",
                    "一再",
                    "一致"
                ],
                "hsk6": [
                    "不屑一顾",
                    "一度",
                    "一帆风顺",
                    "一贯",
                    "一举两得",
                    "一流",
                    "一目了然",
                    "一如既往",
                    "一丝不苟",
                    "一向"
                ],
                "unknown": [
                    "想一想",
                    "一百万"
                ]
            }
        },
        "pinyin_tones": "qing3 rang4 yi1 rang4",
        "function": "idiom",
        "hsk_level": [
            1,
            2,
            1,
            2
        ]
    },
    "小时": {
        "hanzi": "小时",
        "pinyin": "xiǎo shí",
        "literal": "",
        "english": "hour",
        "char_matches": {
            "小": {
                "hsk1": [
                    "小",
                    "小姐"
                ],
                "hsk3": [
                    "小心"
                ],
                "hsk4": [
                    "小吃",
                    "小伙子",
                    "小说"
                ],
                "hsk5": [
                    "胆小鬼",
                    "小麦",
                    "小气"
                ],
                "hsk6": [
                    "渺小",
                    "小心翼翼"
                ]
            },
            "时": {
                "hsk2": [
                    "时间"
                ],
                "hsk1": [
                    "时候"
                ],
                "hsk4": [
                    "按时",
                    "当时",
                    "及时",
                    "平时",
                    "同时",
                    "暂时",
                    "准时"
                ],
                "hsk5": [
                    "临时",
                    "时差",
                    "时代",
                    "时刻",
                    "时髦",
                    "时期",
                    "时尚",
                    "随时"
                ],
                "hsk6": [
                    "不时",
                    "顿时",
                    "时常",
                    "时而",
                    "时光",
                    "时机",
                    "时事"
                ]
            }
        },
        "pinyin_tones": "xiao3 shi2",
        "function": "noun",
        "hsk_level": 2
    },
    "千米": {
        "hanzi": "千米",
        "pinyin": "qiān mǐ",
        "literal": "",
        "english": "kilometer",
        "char_matches": {
            "千": {
                "hsk2": [
                    "千"
                ],
                "hsk4": [
                    "千万"
                ],
                "hsk6": [
                    "千方百计"
                ]
            },
            "米": {
                "hsk1": [
                    "米饭"
                ],
                "hsk3": [
                    "米"
                ],
                "hsk5": [
                    "厘米",
                    "玉米"
                ],
                "hsk6": [
                    "毫米"
                ]
            }
        },
        "pinyin_tones": "qian1 mi3",
        "function": "classifier",
        "hsk_level": -1
    },
    "比": {
        "hanzi": "比",
        "pinyin": "bǐ",
        "literal": "",
        "english": "Belgium / Belgian / abbr. for 比利時|比利时[Bi3 li4 shi2] / euphemistic variant of 屄[bi1] / to compare / (followed by a noun and adjective) more {adj.} than {noun} / ratio / to gesture / (Taiwan pr. [bi4] in some compounds derived from Classical Chinese)",
        "char_matches": {
            "比": {
                "hsk3": [
                    "比较",
                    "比赛"
                ],
                "hsk4": [
                    "比如"
                ],
                "hsk5": [
                    "比例",
                    "对比"
                ],
                "hsk6": [
                    "比方",
                    "比喻",
                    "比重",
                    "无比"
                ]
            }
        },
        "pinyin_tones": "bi3",
        "function": "preposition",
        "hsk_level": 2
    },
    "便宜": {
        "hanzi": "便宜",
        "pinyin": "pián yi",
        "literal": "",
        "english": "convenient / cheap / inexpensive / small advantages / to let sb off lightly",
        "char_matches": {
            "便": {
                "hsk3": [
                    "方便"
                ],
                "hsk4": [
                    "顺便",
                    "随便"
                ],
                "hsk5": [
                    "便"
                ],
                "hsk6": [
                    "便利",
                    "便条",
                    "便于",
                    "即便",
                    "以便"
                ]
            },
            "宜": {
                "hsk6": [
                    "适宜"
                ]
            }
        },
        "pinyin_tones": "pian2 yi",
        "function": "adjective",
        "hsk_level": 2
    },
    "贵": {
        "hanzi": "贵",
        "pinyin": "guì",
        "literal": "",
        "english": "expensive / noble / precious / (honorific) your",
        "char_matches": {
            "贵": {
                "unknown": [
                    "您贵姓"
                ],
                "hsk5": [
                    "宝贵"
                ],
                "hsk6": [
                    "昂贵",
                    "贵族",
                    "难能可贵",
                    "珍贵"
                ]
            }
        },
        "pinyin_tones": "gui4",
        "function": "adjective",
        "hsk_level": 2
    },
    "春": {
        "hanzi": "春",
        "pinyin": "chūn",
        "literal": "",
        "english": "old variant of 春[chun1] / spring (season) / gay / joyful / youthful / love / lust / life / surname Chun",
        "char_matches": {
            "春": {
                "hsk5": [
                    "青春"
                ]
            }
        },
        "pinyin_tones": "chun1",
        "function": "unknown",
        "hsk_level": 3
    },
    "夏": {
        "hanzi": "夏",
        "pinyin": "xià",
        "literal": "",
        "english": "summer / the Xia or Hsia dynasty c. 2000 BC / Xia of the Sixteen Kingdoms (407-432) / surname Xia",
        "char_matches": {
            "夏": {
                "hsk5": [
                    "夏令营"
                ]
            }
        },
        "pinyin_tones": "xia4",
        "function": "proper noun",
        "hsk_level": 3
    },
    "秋": {
        "hanzi": "秋",
        "pinyin": "qiū",
        "literal": "",
        "english": "autumn / fall / harvest time / old variant of 秋[qiu1] / see 鞦韆|秋千[qiu1 qian1] / surname Qiu",
        "char_matches": {},
        "pinyin_tones": "qiu1",
        "function": "unknown",
        "hsk_level": 3
    },
    "冬": {
        "hanzi": "冬",
        "pinyin": "dōng",
        "literal": "",
        "english": "winter / (onom.) beating a drum / rat-a-tat / surname Dong",
        "char_matches": {},
        "pinyin_tones": "dong1",
        "function": "unknown",
        "hsk_level": 3
    },
    "司机": {
        "hanzi": "司机",
        "pinyin": "sī jī",
        "literal": "",
        "english": "chauffeur / driver",
        "char_matches": {
            "司": {
                "hsk2": [
                    "公司"
                ],
                "hsk6": [
                    "打官司",
                    "司法",
                    "司令"
                ],
                "unknown": [
                    "分公司"
                ]
            },
            "机": {
                "hsk2": [
                    "手机",
                    "机场"
                ],
                "hsk1": [
                    "飞机"
                ],
                "hsk3": [
                    "机会",
                    "照相机"
                ],
                "hsk4": [
                    "登机牌"
                ],
                "hsk5": [
                    "机器"
                ],
                "hsk6": [
                    "动机",
                    "机动",
                    "机构",
                    "机灵",
                    "机密",
                    "机械",
                    "机遇",
                    "机智",
                    "生机",
                    "时机",
                    "收音机",
                    "投机",
                    "危机"
                ]
            }
        },
        "pinyin_tones": "si1 ji1",
        "function": "noun",
        "hsk_level": 3
    },
    "丑": {
        "hanzi": "丑",
        "pinyin": "chǒu",
        "literal": "",
        "english": "clown / 2nd earthly branch: 1-3 a.m., 12th solar month (6th January to 3rd February), year of the Ox / ancient Chinese compass point: 30° / shameful / ugly / disgraceful / surname Chou",
        "char_matches": {
            "丑": {
                "hsk6": [
                    "丑恶"
                ]
            }
        },
        "pinyin_tones": "chou3",
        "function": "adjective",
        "hsk_level": 5
    },
    "吧": {
        "hanzi": "吧",
        "pinyin": "ba",
        "literal": "",
        "english": "bar (loanword) (serving drinks, or providing Internet access etc) / to puff (on a pipe etc) / (onom.) bang / abbr. for 貼吧|贴吧[tie1 ba1] / (modal particle indicating suggestion or surmise) / ...right? / ...OK? / ...I presume. / (onom.) smack!",
        "char_matches": {
            "吧": {
                "hsk5": [
                    "酒吧"
                ]
            }
        },
        "pinyin_tones": "ba",
        "function": "language-particle",
        "hsk_level": 2
    },
    "啊": {
        "hanzi": "啊",
        "pinyin": "a",
        "literal": "",
        "english": "interjection of surprise / Ah! / Oh! / interjection expressing doubt or requiring answer / Eh? / what? / interjection of surprise or doubt / Eh? / My! / what's up? / interjection or grunt of agreement / uhm / Ah, OK / expression of recognition / Oh, it's you! / modal particle ending sentence, showing affirmation, approval, or consent",
        "char_matches": {},
        "pinyin_tones": "a",
        "function": "unknown",
        "hsk_level": 3
    },
    "广东": {
        "hanzi": "广东",
        "pinyin": "guǎng dōng",
        "literal": "",
        "english": "Guangdong province (Kwangtung) in south China, short name 粵|粤[Yue4], capital Guangzhou 廣州|广州",
        "char_matches": {
            "广": {
                "hsk4": [
                    "广播",
                    "广告"
                ],
                "hsk5": [
                    "广场",
                    "广大",
                    "广泛",
                    "推广"
                ],
                "hsk6": [
                    "广阔",
                    "见多识广"
                ]
            },
            "东": {
                "hsk1": [
                    "东西"
                ],
                "hsk3": [
                    "东"
                ],
                "hsk4": [
                    "房东"
                ],
                "hsk6": [
                    "东道主",
                    "东张西望",
                    "股东"
                ],
                "unknown": [
                    "东南西北",
                    "东方学院"
                ]
            }
        },
        "pinyin_tones": "guang3 dong1",
        "function": "place noun",
        "hsk_level": -1
    },
    "年纪": {
        "hanzi": "年纪",
        "pinyin": "nián jì",
        "literal": "",
        "english": "age",
        "char_matches": {
            "年": {
                "hsk1": [
                    "年"
                ],
                "hsk2": [
                    "去年"
                ],
                "hsk3": [
                    "年级",
                    "年轻"
                ],
                "hsk4": [
                    "年龄"
                ],
                "hsk5": [
                    "年代",
                    "青少年"
                ],
                "hsk6": [
                    "拜年",
                    "连年",
                    "年度",
                    "周年",
                    "逐年"
                ]
            },
            "纪": {
                "hsk4": [
                    "世纪"
                ],
                "hsk5": [
                    "纪录",
                    "纪律",
                    "纪念"
                ],
                "hsk6": [
                    "纪要"
                ]
            }
        },
        "pinyin_tones": "nian2 ji4",
        "function": "unknown",
        "hsk_level": 5
    },
    "有意思": {
        "hanzi": "有意思",
        "pinyin": "yǒu yì sī",
        "literal": "",
        "english": "interesting / meaningful / enjoyable / fun",
        "char_matches": {
            "有": {
                "hsk1": [
                    "有",
                    "没有"
                ],
                "hsk3": [
                    "有名",
                    "只有"
                ],
                "hsk4": [
                    "所有",
                    "有趣"
                ],
                "hsk5": [
                    "有利"
                ],
                "hsk6": [
                    "固有",
                    "津津有味",
                    "岂有此理",
                    "拥有",
                    "有条不紊"
                ],
                "unknown": [
                    "有兴趣"
                ]
            },
            "意": {
                "hsk2": [
                    "意思"
                ],
                "hsk3": [
                    "满意",
                    "同意",
                    "愿意",
                    "注意"
                ],
                "hsk4": [
                    "得意",
                    "故意",
                    "生意",
                    "意见",
                    "主意"
                ],
                "hsk5": [
                    "意外",
                    "意义"
                ],
                "hsk6": [
                    "称心如意",
                    "大意",
                    "乐意",
                    "任意",
                    "示意",
                    "随意",
                    "特意",
                    "玩意儿",
                    "意料",
                    "意识",
                    "意图",
                    "意味着",
                    "意向",
                    "意志",
                    "在意"
                ]
            },
            "思": {
                "hsk2": [
                    "意思"
                ],
                "hsk5": [
                    "思考",
                    "思想"
                ],
                "hsk6": [
                    "不可思议",
                    "沉思",
                    "反思",
                    "构思",
                    "思念",
                    "思索",
                    "思维"
                ]
            }
        },
        "pinyin_tones": "you3 yi4 si1",
        "function": "temporary word",
        "hsk_level": -1
    },
    "文化": {
        "hanzi": "文化",
        "pinyin": "wén huà",
        "literal": "",
        "english": "culture / civilization / cultural",
        "char_matches": {
            "文": {
                "hsk3": [
                    "中文"
                ],
                "hsk4": [
                    "文章"
                ],
                "hsk5": [
                    "论文",
                    "文件",
                    "文具",
                    "文明",
                    "文学",
                    "文字",
                    "作文"
                ],
                "hsk6": [
                    "散文",
                    "斯文",
                    "天文",
                    "文凭",
                    "文物",
                    "文献",
                    "文雅",
                    "文艺"
                ],
                "unknown": [
                    "不说中文"
                ]
            },
            "化": {
                "hsk3": [
                    "变化"
                ],
                "hsk5": [
                    "化学",
                    "消化"
                ],
                "hsk6": [
                    "多元化",
                    "恶化",
                    "二氧化碳",
                    "化肥",
                    "化石",
                    "化验",
                    "化妆",
                    "简化",
                    "进化",
                    "潜移默化",
                    "融化"
                ]
            }
        },
        "pinyin_tones": "wen2 hua4",
        "function": "noun",
        "hsk_level": 3
    },
    "对": {
        "hanzi": "对",
        "pinyin": "duì",
        "literal": "",
        "english": "right / correct / couple / pair / towards / at / for / to face / opposite / to treat (sb a certain way) / to match together / to adjust / to fit / to suit / to answer / to reply / classifier: couple",
        "char_matches": {
            "对": {
                "hsk1": [
                    "对不起"
                ],
                "hsk4": [
                    "对话",
                    "对面",
                    "对于",
                    "反对"
                ],
                "hsk5": [
                    "对比",
                    "对待",
                    "对方",
                    "对手",
                    "对象",
                    "绝对",
                    "面对",
                    "相对",
                    "针对"
                ],
                "hsk6": [
                    "对策",
                    "对称",
                    "对付",
                    "对抗",
                    "对立",
                    "对联",
                    "对应",
                    "对照"
                ]
            }
        },
        "pinyin_tones": "dui4",
        "function": "preposition",
        "hsk_level": 2
    },
    "有兴趣": {
        "hanzi": "有兴趣",
        "pinyin": "yǒu xìng qù",
        "literal": "",
        "english": "interested / interesting",
        "char_matches": {
            "有": {
                "hsk1": [
                    "有",
                    "没有"
                ],
                "hsk3": [
                    "有名",
                    "只有"
                ],
                "hsk4": [
                    "所有",
                    "有趣"
                ],
                "hsk5": [
                    "有利"
                ],
                "hsk6": [
                    "固有",
                    "津津有味",
                    "岂有此理",
                    "拥有",
                    "有条不紊"
                ],
                "unknown": [
                    "有意思"
                ]
            },
            "兴": {
                "hsk1": [
                    "高兴"
                ],
                "hsk3": [
                    "感兴趣"
                ],
                "hsk4": [
                    "兴奋"
                ],
                "hsk6": [
                    "复兴",
                    "兴隆",
                    "兴旺",
                    "兴高采烈",
                    "兴致勃勃",
                    "振兴"
                ]
            },
            "趣": {
                "hsk3": [
                    "感兴趣"
                ],
                "hsk4": [
                    "有趣"
                ],
                "hsk6": [
                    "风趣",
                    "乐趣",
                    "趣味"
                ]
            }
        },
        "pinyin_tones": "you3 xing4 qu4",
        "function": [
            "verb",
            "noun"
        ],
        "hsk_level": [
            1,
            -1
        ]
    },
    "一百万": {
        "hanzi": "一百万",
        "pinyin": "yì bǎi wàn",
        "literal": "",
        "english": "one million",
        "char_matches": {
            "一": {
                "hsk1": [
                    "一",
                    "一点儿"
                ],
                "hsk2": [
                    "第一",
                    "一起",
                    "一下"
                ],
                "hsk3": [
                    "一般",
                    "一边",
                    "一定",
                    "一共",
                    "一会儿",
                    "一样",
                    "一直"
                ],
                "hsk4": [
                    "一切"
                ],
                "hsk5": [
                    "统一",
                    "万一",
                    "唯一",
                    "一辈子",
                    "一旦",
                    "一律",
                    "一再",
                    "一致"
                ],
                "hsk6": [
                    "不屑一顾",
                    "一度",
                    "一帆风顺",
                    "一贯",
                    "一举两得",
                    "一流",
                    "一目了然",
                    "一如既往",
                    "一丝不苟",
                    "一向"
                ],
                "unknown": [
                    "想一想",
                    "请让一让"
                ]
            },
            "百": {
                "hsk2": [
                    "百"
                ],
                "hsk4": [
                    "百分之"
                ],
                "hsk5": [
                    "老百姓"
                ],
                "hsk6": [
                    "千方百计"
                ]
            },
            "万": {
                "hsk3": [
                    "万"
                ],
                "hsk4": [
                    "千万"
                ],
                "hsk5": [
                    "万一"
                ],
                "hsk6": [
                    "万分"
                ]
            }
        },
        "pinyin_tones": "yi4 bai3 wan4",
        "function": "number",
        "hsk_level": 1
    },
    "抽": {
        "hanzi": "抽",
        "pinyin": "chōu",
        "literal": "",
        "english": "to draw out / to pull out from in between / to remove part of the whole / (of certain plants) to sprout or bud / to whip or thrash",
        "char_matches": {},
        "pinyin_tones": "chou1",
        "function": "verb",
        "hsk_level": -1
    },
    "地下": {
        "hanzi": "地下",
        "pinyin": "dì xià",
        "literal": "",
        "english": "underground / subterranean / covert",
        "char_matches": {},
        "pinyin_tones": "di4 xia4",
        "function": "unknown",
        "hsk_level": -1
    },
    "地上": {
        "hanzi": "地上",
        "pinyin": "dì shàng",
        "literal": "",
        "english": "on the ground / on the floor",
        "char_matches": {},
        "pinyin_tones": "di4 shang4",
        "function": "unknown",
        "hsk_level": -1
    },
    "地图": {
        "hanzi": "地图",
        "pinyin": "dì tú",
        "literal": "",
        "english": "map",
        "char_matches": {},
        "pinyin_tones": "di4 tu2",
        "function": "noun",
        "hsk_level": 3
    },
    "地球": {
        "hanzi": "地球",
        "pinyin": "dì qiú",
        "literal": "",
        "english": "the earth",
        "char_matches": {},
        "pinyin_tones": "di4 qiu2",
        "function": "noun",
        "hsk_level": 4
    },
    "足球": {
        "hanzi": "足球",
        "pinyin": "zú qiú",
        "literal": "",
        "english": "soccer ball / a football / soccer / football",
        "char_matches": {},
        "pinyin_tones": "zu2 qiu2",
        "function": "noun",
        "hsk_level": -1
    },
    "天下大同": {
        "hanzi": "天下大同",
        "pinyin": "tiān xià dà tóng",
        "literal": "",
        "english": "the whole world as one family",
        "char_matches": {},
        "pinyin_tones": "tian1 xia4 da4 tong2",
        "function": "temporary word",
        "hsk_level": -1
    },
    "世界是一家": {
        "hanzi": "世界是一家",
        "pinyin": "shì jiè shì yī jiā",
        "literal": "",
        "english": "the world is one family",
        "char_matches": {},
        "pinyin_tones": "shi4 jie4 shi4 yi1 jia1",
        "function": [
            "noun",
            "verb",
            "number"
        ],
        "hsk_level": [
            3,
            1,
            -1
        ]
    },
    "看朋友": {
        "hanzi": "看朋友",
        "pinyin": "kàn péng yǒu",
        "literal": "",
        "english": "to visit friend(s)",
        "char_matches": {},
        "pinyin_tones": "kan4 peng2 you3",
        "function": [
            "verb",
            "noun"
        ],
        "hsk_level": [
            1,
            1
        ]
    },
    "毛": {
        "hanzi": "毛",
        "pinyin": "máo",
        "literal": "",
        "english": "hair / feather / down / wool / mildew / mold / coarse or semifinished / young / raw / careless / unthinking / nervous / scared / (of currency) to devalue or depreciate / classifier for Chinese fractional monetary unit ( = 角[jiao3] , = one-tenth of a yuan or 10 fen 分[fen1]) / surname Mao",
        "char_matches": {},
        "pinyin_tones": "mao2",
        "function": "proper noun",
        "hsk_level": 4
    },
    "笔": {
        "hanzi": "笔",
        "pinyin": "bǐ",
        "literal": "",
        "english": "pen / pencil / writing brush / to write or compose / the strokes of Chinese characters / classifier for sums of money, deals",
        "char_matches": {},
        "pinyin_tones": "bi3",
        "function": "noun",
        "hsk_level": -1
    },
    "世界地图": {
        "hanzi": "世界地图",
        "pinyin": "shì jiè dì tú",
        "literal": "",
        "english": "world map",
        "char_matches": {},
        "pinyin_tones": "shi4 jie4 di4 tu2",
        "function": "other noun",
        "hsk_level": -1
    },
    "苦": {
        "hanzi": "苦",
        "pinyin": "kǔ",
        "literal": "",
        "english": "bitter / hardship / pain / to suffer / to bring suffering to / painstakingly",
        "char_matches": {},
        "pinyin_tones": "ku3",
        "function": "adjective",
        "hsk_level": 4
    },
    "干": {
        "hanzi": "干",
        "pinyin": "gàn",
        "literal": "",
        "english": "old variant of 乾|干[gan1] / dry / clean / in vain / dried food / foster / adoptive / to ignore / variant of 乾|干[gan1] / to concern / to interfere / shield / stem / tree trunk / main part of sth / to manage / to work / to do / capable / cadre / to kill (slang) / to fuck (vulgar) / surname Gan",
        "char_matches": {},
        "pinyin_tones": "gan4",
        "function": "verb",
        "hsk_level": 4
    },
    "感冒": {
        "hanzi": "感冒",
        "pinyin": "gǎn mào",
        "literal": "",
        "english": "to catch cold / (common) cold / (coll.) to be interested in (often used in the negative) / (Tw) to detest / can't stand",
        "char_matches": {},
        "pinyin_tones": "gan3 mao4",
        "function": "verb",
        "hsk_level": 3
    },
    "感": {
        "hanzi": "感",
        "pinyin": "gǎn",
        "literal": "",
        "english": "to feel / to move / to touch / to affect / feeling / emotion / (suffix) sense of ~",
        "char_matches": {},
        "pinyin_tones": "gan3",
        "function": "verb",
        "hsk_level": -1
    },
    "要": {
        "hanzi": "要",
        "pinyin": "yào",
        "literal": "",
        "english": "to demand / to request / to coerce / important / vital / to want / to ask for / will / going to (as future auxiliary) / may / must / (used in a comparison) must be / probably / if",
        "char_matches": {},
        "pinyin_tones": "yao4",
        "function": "verb",
        "hsk_level": 2
    },
    "听一下": {
        "hanzi": "听一下",
        "pinyin": "tīng yī xià",
        "literal": "",
        "english": "",
        "char_matches": {},
        "pinyin_tones": "ting1 yi1 xia4",
        "function": [
            "verb",
            "number"
        ],
        "hsk_level": [
            1,
            2
        ]
    },
    "厕所": {
        "hanzi": "厕所",
        "pinyin": "cè suǒ",
        "literal": "",
        "english": "toilet / lavatory",
        "char_matches": {},
        "pinyin_tones": "ce4 suo3",
        "function": "noun",
        "hsk_level": 4
    },
    "歌": {
        "hanzi": "歌",
        "pinyin": "gē",
        "literal": "",
        "english": "song / to sing / variant of 歌[ge1]",
        "char_matches": {},
        "pinyin_tones": "ge1",
        "function": "noun",
        "hsk_level": -1
    },
    "行": {
        "hanzi": "行",
        "pinyin": "xíng",
        "literal": "",
        "english": "row / line / commercial firm / line of business / profession / to rank (first, second etc) among one's siblings (by age) / (in data tables) row / (Tw) column / to walk / to go / to travel / a visit / temporary / makeshift / current / in circulation / to do / to perform / capable / competent / effective / all right / OK! / will do / behavior / conduct / Taiwan pr. [xing4] for the behavior-conduct sense",
        "char_matches": {},
        "pinyin_tones": "xing2",
        "function": "unknown",
        "hsk_level": 4
    },
    "比较": {
        "hanzi": "比较",
        "pinyin": "bǐ jiào",
        "literal": "",
        "english": "to compare / to contrast / comparatively / relatively / quite / comparison",
        "char_matches": {},
        "pinyin_tones": "bi3 jiao4",
        "function": "adverb",
        "hsk_level": 3
    },
    "张": {
        "hanzi": "张",
        "pinyin": "zhāng",
        "literal": "",
        "english": "to open up / to spread / sheet of paper / classifier for flat objects, sheet / classifier for votes / surname Zhang",
        "char_matches": {},
        "pinyin_tones": "zhang1",
        "function": "classifier",
        "hsk_level": 3
    },
    "一下": {
        "hanzi": "一下",
        "pinyin": "yī xià",
        "literal": "",
        "english": "(used after a verb) give it a go / to do (sth for a bit to give it a try) / one time / once / in a while / all of a sudden / all at once",
        "char_matches": {},
        "pinyin_tones": "yi1 xia4",
        "function": "number",
        "hsk_level": 2
    },
    "支": {
        "hanzi": "支",
        "pinyin": "zhī",
        "literal": "",
        "english": "to support / to sustain / to erect / to raise / branch / division / to draw money / classifier for rods such as pens and guns, for army divisions and for songs or compositions / surname Zhi",
        "char_matches": {},
        "pinyin_tones": "zhi1",
        "function": "noun",
        "hsk_level": 5
    },
    "本": {
        "hanzi": "本",
        "pinyin": "běn",
        "literal": "",
        "english": "root / stem / origin / source / this / the current / original / inherent / originally / classifier for books, periodicals, files etc",
        "char_matches": {},
        "pinyin_tones": "ben3",
        "function": "pronoun",
        "hsk_level": 1
    },
    "历史": {
        "hanzi": "历史",
        "pinyin": "lì shǐ",
        "literal": "",
        "english": "history",
        "char_matches": {},
        "pinyin_tones": "li4 shi3",
        "function": "noun",
        "hsk_level": 3
    },
    "书": {
        "hanzi": "书",
        "pinyin": "shū",
        "literal": "",
        "english": "abbr. for 書經|书经[Shu1 jing1] / book / letter / document / to write",
        "char_matches": {},
        "pinyin_tones": "shu1",
        "function": "noun",
        "hsk_level": 1
    },
    "本子": {
        "hanzi": "本子",
        "pinyin": "běn zi",
        "literal": "",
        "english": "book / notebook / Japanese-style self-published comic (esp. an erotic one), aka \"dōjinshi\" / edition",
        "char_matches": {},
        "pinyin_tones": "ben3 zi",
        "function": "noun",
        "hsk_level": -1
    },
    "请问": {
        "hanzi": "请问",
        "pinyin": "qǐng wèn",
        "literal": "",
        "english": "Excuse me, may I ask...?",
        "char_matches": {},
        "pinyin_tones": "qing3 wen4",
        "function": "verb",
        "hsk_level": -1
    },
    "问": {
        "hanzi": "问",
        "pinyin": "wèn",
        "literal": "",
        "english": "to ask",
        "char_matches": {},
        "pinyin_tones": "wen4",
        "function": "noun",
        "hsk_level": 2
    },
    "词典": {
        "hanzi": "词典",
        "pinyin": "cí diǎn",
        "literal": "",
        "english": "dictionary / also written 辭典|辞典[ci2 dian3]",
        "char_matches": {},
        "pinyin_tones": "ci2 dian3",
        "function": "noun",
        "hsk_level": 3
    },
    "用": {
        "hanzi": "用",
        "pinyin": "yòng",
        "literal": "",
        "english": "to use / to employ / to have to / to eat or drink / expense or outlay / usefulness / hence / therefore",
        "char_matches": {},
        "pinyin_tones": "yong4",
        "function": "preposition",
        "hsk_level": 3
    },
    "有用": {
        "hanzi": "有用",
        "pinyin": "yǒu yòng",
        "literal": "",
        "english": "useful",
        "char_matches": {},
        "pinyin_tones": "you3 yong4",
        "function": "verb",
        "hsk_level": -1
    },
    "谁": {
        "hanzi": "谁",
        "pinyin": "shuí",
        "literal": "",
        "english": "who / also pr. [shui2]",
        "char_matches": {},
        "pinyin_tones": "shui2",
        "function": "pronoun",
        "hsk_level": 1
    },
    "经济": {
        "hanzi": "经济",
        "pinyin": "jīng jì",
        "literal": "",
        "english": "economy / economic",
        "char_matches": {},
        "pinyin_tones": "jing1 ji4",
        "function": "noun",
        "hsk_level": 4
    }
}